README.md
setup.py
ploi/__init__.py
ploi/ploi.py
ploi.egg-info/PKG-INFO
ploi.egg-info/SOURCES.txt
ploi.egg-info/dependency_links.txt
ploi.egg-info/requires.txt
ploi.egg-info/top_level.txt