Metadata-Version: 1.0
Name: ploi
Version: 1.0.1
Summary: A Python package to interact with Ploi API.
Home-page: https://github.com/rehmatworks/ploi-python
Author: Rehmat
Author-email: contact@rehmat.works
License: MIT
Platform: UNKNOWN
